doc/release.md
hwdocer/__init__.py
hwdocer/__main__.py
hwdocer/hwdocer.py
hwdocer/version.py
hwdocer-0.2.2.dist-info/METADATA
hwdocer-0.2.2.dist-info/WHEEL
hwdocer-0.2.2.dist-info/entry_points.txt
hwdocer-0.2.2.dist-info/RECORD
