Metadata-Version: 2.1
Name: hwdocer
Version: 0.2.2
Summary: Wireviz, drawio and other documentation build tool
Home-page: https://gitlab.com/real-ee/public/hwdocer
License: GPL-3.0-or-later
Keywords: drawio,wireviz,toolchain,automation,documentation
Author: Laurence DV
Author-email: laurencedv@realee.tech
Requires-Python: >=3.8,<4.0
Classifier: Development Status :: 3 - Alpha
Classifier: Environment :: Console
Classifier: Intended Audience :: Developers
Classifier: License :: OSI Approved :: GNU General Public License v3 or later (GPLv3+)
Classifier: Operating System :: POSIX :: Linux
Classifier: Programming Language :: Python :: 3
Classifier: Programming Language :: Python :: 3.8
Classifier: Programming Language :: Python :: 3.9
Classifier: Programming Language :: Python :: 3.10
Classifier: Programming Language :: Python :: 3.11
Classifier: Programming Language :: Python :: 3.12
Classifier: Topic :: Documentation
Classifier: Topic :: Multimedia :: Graphics
Classifier: Topic :: Scientific/Engineering
Classifier: Topic :: Software Development :: Documentation
Classifier: Topic :: Utilities
Requires-Dist: drawio (>=0.0.10,<0.0.11)
Requires-Dist: pyyaml (>=6.0.1,<7.0.0)
Requires-Dist: rich (>=13.7.1,<14.0.0)
Requires-Dist: wireviz (>=0.3.2,<0.4.0)
Project-URL: Changelog, https://gitlab.com/real-ee/public/hwdocer/-/blob/master/doc/release.md
Project-URL: Contribution, https://gitlab.com/real-ee/public/hwdocer/-/blob/master/doc/contrib.md?ref_type=heads
Project-URL: Documentation, https://gitlab.com/real-ee/public/hwdocer/-/tree/master/doc
Project-URL: Issue, https://gitlab.com/real-ee/public/hwdocer/-/issues
Project-URL: Repository, https://gitlab.com/real-ee/public/hwdocer
Project-URL: Roadmap, https://gitlab.com/real-ee/public/hwdocer/-/blob/master/doc/roadmap.md
